dolly/__init__.py
dolly/project.py
dolly/v_list_dirs.py
dolly/v_count.py
dolly/testadd.py
dolly/v_update.py
dolly/util.py
dolly/v_list.py
dolly/config.py
dolly/v_status.py
dolly/dolly.py
dolly/v_install.py
dolly/terminal.py
dolly/__main__.py
Dolly-0.1.0.dist-info/top_level.txt
Dolly-0.1.0.dist-info/metadata.json
Dolly-0.1.0.dist-info/entry_points.txt
Dolly-0.1.0.dist-info/WHEEL
Dolly-0.1.0.dist-info/RECORD
Dolly-0.1.0.dist-info/DESCRIPTION.rst
Dolly-0.1.0.dist-info/METADATA
