Metadata-Version: 2.0
Name: Dolly
Version: 0.1.0
Summary: Dolly manages multiple git and svn repos
Home-page: UNKNOWN
Author: UNKNOWN
Author-email: UNKNOWN
License: UNKNOWN
Platform: UNKNOWN
Requires-Dist: pyyaml
Requires-Dist: argparse
